{"title":"Michael1","uid":5659689,"size":1790634796,"categoryP":"video","categoryS":"music_videos","magnet":"?xt=urn:btih:000a03ac075cd4caf0015fb1fa9d97bf5e289de9&amp;dn=Michael1&amp;tr=udp%3A%2F%2Ftracker.openbittorrent.com%3A80&amp;tr=udp%3A%2F%2Fopen.demonii.com%3A1337&amp;tr=udp%3A%2F%2Ftracker.coppersurfer.tk%3A6969&amp;tr=udp%3A%2F%2Fexodus.desync.com%3A6969","seeders":0,"leechers":0,"uploader":"GamesHiJackeR","files":17,"time":1277927170,"description":"The most want songs of Michael Jackson.\nDvD video quality.\nIt may take you a week or two to download. But it is worth it.\nyou can join all the files together using some software to make one complete DVD.","torrent":{"xt":"urn:btih:000a03ac075cd4caf0015fb1fa9d97bf5e289de9","amp;dn":"Michael1","amp;tr":["udp%3A%2F%2Ftracker.openbittorrent.com%3A80","udp%3A%2F%2Fopen.demonii.com%3A1337","udp%3A%2F%2Ftracker.coppersurfer.tk%3A6969","udp%3A%2F%2Fexodus.desync.com%3A6969"],"infoHash":"000a03ac075cd4caf0015fb1fa9d97bf5e289de9","infoHashBuffer":{"type":"Buffer","data":[0,10,3,172,7,92,212,202,240,1,95,177,250,157,151,191,94,40,157,233]},"announce":[],"urlList":[]}}