{"title":"Hofo september pack 2009","uid":5128225,"size":304112019,"categoryP":"audio","categoryS":"music","magnet":"?xt=urn:btih:0291364bd026494bb40bdc1dbbc0d58cdc5ec34a&amp;dn=Hofo+september+pack+2009&amp;tr=udp%3A%2F%2Ftracker.openbittorrent.com%3A80&amp;tr=udp%3A%2F%2Fopen.demonii.com%3A1337&amp;tr=udp%3A%2F%2Ftracker.coppersurfer.tk%3A6969&amp;tr=udp%3A%2F%2Fexodus.desync.com%3A6969","seeders":0,"leechers":0,"uploader":"SKrubbe","files":39,"time":1255799006,"description":"Hofo september pack 2009 !\n\n---Swedish---\n\nDet hÃƒÂ¤r packet inehÃƒÂ¥ller alla lÃƒÂ¥tar frÃƒÂ¥n hofo.se under september 2009.\nVi lÃƒÂ¤gger upp ett pack varje mÃƒÂ¥nad som innehÃƒÂ¥ller den nyaste musiken samt nÃƒÂ¥gra skÃƒÂ¶na oldies !\n\n\n\n--English---\n\nAll tracks from september 2009 at hofo.se\nWe will release a new hofo pack every month with the newest music for you.\n\n\n\n-- Tracklist --\n\n\nEchoillusion - Energy 2k9 \nStian K - Be Alive! (Lasj rmx) \nSammie Bounce - Back In Time (Sebbit Remix) \nTop Tec - (bassbross - Bianca - Top Tec RmX)  \nAlice Deejay - Better Off Alone (Sebbit Remix)\nShine DJs - Forever Autumn (Radio Edit)  \nAntebrink Och Digitunez - Hand i hand \nBassbros - Bianca(SankeY Inc. Remix 09) \nBasse - Inget stoppar oss nu \nBoom - How Do You Do (Lucas One Remix) \nBoozer - Start Boozing \nBoozer - The One ( Original Mix ) \nCascada - What do you want from me (DJ V3N0M RMX) \nD3Y - Beat Echo (Tobbaz Remix) \nDavid K - Flickan i Minnet   \nDigitunez - Inget kan stoppa oss nu   \nDJ Auzern - 3rd Base (CmC Rmx!!) \nDj Fegge - Dont Stop [ 2009 ]   \nDj Squash - Lucky Times (Original Mix) \nE.M.J - Clubwalker (Original Mix) \nHarder, better, faster, stronger \nKick - Fest hos mig (Ajan-m Re-mix) \nKidooMusic- Du ÃƒÂ¤r min bÃƒÂ¤jbi ( Dance remix ) \nLaser Inc. - NÃƒÂ¤r man var liten (DJ V3N0M RMX) \nLucas One - You Wanna Rock  \nMaster Blaster - Come Clean (Lucas One Remix) \nMax Mafia - Trumpet Girls (Original Edit)  \nNiklas J &amp; Calle A - Girl Next Door! (Redtzer Remix) \nNordic Stars - Jump Jump (Bassbrazzer Remix)  \nRam Jam - Black Betty (The Mobb Remix) \nRednexCottoneyedjoeNiczRemix  \nSean Kingston - Beautiful Girl (DJ V3N0M RMX)  \nShine DJs - Forever Autumn (Matt Martin Extended Mix) \nSidechainerz - Right Here (Tobbaz Remix)  \nSpace Cowboy And Chelsea - Falling Down (Digitunez mix)   \nToby &amp; Pino - When Life Breaks Down \nToby n Freda - Maybe (Bassbrazzer Remix) - bassbrazzer.com \nTURN - Primitive future \nZone Breaker - Crazy Moves (Sebbit Remix) \n","torrent":{"xt":"urn:btih:0291364bd026494bb40bdc1dbbc0d58cdc5ec34a","amp;dn":"Hofo+september+pack+2009","amp;tr":["udp%3A%2F%2Ftracker.openbittorrent.com%3A80","udp%3A%2F%2Fopen.demonii.com%3A1337","udp%3A%2F%2Ftracker.coppersurfer.tk%3A6969","udp%3A%2F%2Fexodus.desync.com%3A6969"],"infoHash":"0291364bd026494bb40bdc1dbbc0d58cdc5ec34a","infoHashBuffer":{"type":"Buffer","data":[2,145,54,75,208,38,73,75,180,11,220,29,187,192,213,140,220,94,195,74]},"announce":[],"urlList":[]}}