{"title":"Teen blonde in homemade","uid":5082235,"size":67690010,"categoryP":"porn","categoryS":"movie_clips","magnet":"?xt=urn:btih:145ec6ce413c8995cad4094ce10c24b989efda69&amp;dn=Teen+blonde+in+homemade&amp;tr=udp%3A%2F%2Ftracker.openbittorrent.com%3A80&amp;tr=udp%3A%2F%2Fopen.demonii.com%3A1337&amp;tr=udp%3A%2F%2Ftracker.coppersurfer.tk%3A6969&amp;tr=udp%3A%2F%2Fexodus.desync.com%3A6969","seeders":0,"leechers":0,"uploader":"beta2008x","files":1,"time":1252425728,"description":"Very nice girl home video by her beside her best friend, a video that does not have waste from start to finish.\n\nScreen:\n &lt;a href=&quot;\nhttp://www.dumppix.com/viewer.php?file=vzhgy9jt9n4bi860wo91.jpg&quot; rel=&quot;nofollow&quot; target=&quot;_NEW&quot;&gt;\nhttp://www.dumppix.com/viewer.php?file=vzhgy9jt9n4bi860wo91.jpg&lt;/a&gt;","torrent":{"xt":"urn:btih:145ec6ce413c8995cad4094ce10c24b989efda69","amp;dn":"Teen+blonde+in+homemade","amp;tr":["udp%3A%2F%2Ftracker.openbittorrent.com%3A80","udp%3A%2F%2Fopen.demonii.com%3A1337","udp%3A%2F%2Ftracker.coppersurfer.tk%3A6969","udp%3A%2F%2Fexodus.desync.com%3A6969"],"infoHash":"145ec6ce413c8995cad4094ce10c24b989efda69","infoHashBuffer":{"type":"Buffer","data":[20,94,198,206,65,60,137,149,202,212,9,76,225,12,36,185,137,239,218,105]},"announce":[],"urlList":[]}}