{"title":"Il Divos - Svenskaspel","uid":5573109,"size":2490990592,"categoryP":"video","categoryS":"movie_clips","magnet":"?xt=urn:btih:1b46351a02227ee14ba69b069af35c53120bbc17&amp;dn=Il+Divos+-+Svenskaspel&amp;tr=udp%3A%2F%2Ftracker.openbittorrent.com%3A80&amp;tr=udp%3A%2F%2Fopen.demonii.com%3A1337&amp;tr=udp%3A%2F%2Ftracker.coppersurfer.tk%3A6969&amp;tr=udp%3A%2F%2Fexodus.desync.com%3A6969","seeders":0,"leechers":0,"uploader":"Roffeus","files":3,"time":1274306406,"description":"AlingsÃƒÂ¥skorpen 2010, omgÃƒÂ¥ng 2\n\nIl Divos - Svenskaspel","torrent":{"xt":"urn:btih:1b46351a02227ee14ba69b069af35c53120bbc17","amp;dn":"Il+Divos+-+Svenskaspel","amp;tr":["udp%3A%2F%2Ftracker.openbittorrent.com%3A80","udp%3A%2F%2Fopen.demonii.com%3A1337","udp%3A%2F%2Ftracker.coppersurfer.tk%3A6969","udp%3A%2F%2Fexodus.desync.com%3A6969"],"infoHash":"1b46351a02227ee14ba69b069af35c53120bbc17","infoHashBuffer":{"type":"Buffer","data":[27,70,53,26,2,34,126,225,75,166,155,6,154,243,92,83,18,11,188,23]},"announce":[],"urlList":[]}}