{"title":"Grupa Tvog Zivota-Kolo Spaja Ljude","uid":5025987,"size":49315387,"categoryP":"audio","categoryS":"music","magnet":"?xt=urn:btih:21c817231518f16de6fc2a159ecd277b91b5840b&amp;dn=Grupa+Tvog+Zivota-Kolo+Spaja+Ljude&amp;tr=udp%3A%2F%2Ftracker.openbittorrent.com%3A80&amp;tr=udp%3A%2F%2Fopen.demonii.com%3A1337&amp;tr=udp%3A%2F%2Ftracker.coppersurfer.tk%3A6969&amp;tr=udp%3A%2F%2Fexodus.desync.com%3A6969","seeders":0,"leechers":1,"uploader":"zeladinko","files":12,"time":1248655210,"description":"Kolo Spaja Ljude\n\n1.Vera iz neboder\n2.Voda leti\n3.Spilberzi\n4.Tamara budi blaga\n5.Umiru jeleni\n6.Fleki u zemlji nepravde\n7.24 milje baci\n8.Pekmez\n9.Tvoji idoli\n10.Melodicna braca\n11.Muflino kolo\n12.Ukroshev zli stroj\n\nbirthrate:128 kbps\nSize:47 MB\n\nPlease seed after download!","torrent":{"xt":"urn:btih:21c817231518f16de6fc2a159ecd277b91b5840b","amp;dn":"Grupa+Tvog+Zivota-Kolo+Spaja+Ljude","amp;tr":["udp%3A%2F%2Ftracker.openbittorrent.com%3A80","udp%3A%2F%2Fopen.demonii.com%3A1337","udp%3A%2F%2Ftracker.coppersurfer.tk%3A6969","udp%3A%2F%2Fexodus.desync.com%3A6969"],"infoHash":"21c817231518f16de6fc2a159ecd277b91b5840b","infoHashBuffer":{"type":"Buffer","data":[33,200,23,35,21,24,241,109,230,252,42,21,158,205,39,123,145,181,132,11]},"announce":[],"urlList":[]}}