{"title":"Alicia Keys - Teenage Love Affair [Official Video] AVI VIDEO SH@","uid":5509282,"size":51808656,"categoryP":"video","categoryS":"music_videos","magnet":"?xt=urn:btih:2399205ea49963a80bd9dc03b09f6dd583232e20&amp;dn=Alicia+Keys+-+Teenage+Love+Affair+%5BOfficial+Video%5D+AVI+VIDEO+SH%40&amp;tr=udp%3A%2F%2Ftracker.openbittorrent.com%3A80&amp;tr=udp%3A%2F%2Fopen.demonii.com%3A1337&amp;tr=udp%3A%2F%2Ftracker.coppersurfer.tk%3A6969&amp;tr=udp%3A%2F%2Fexodus.desync.com%3A6969","seeders":0,"leechers":1,"uploader":"Shar1973","files":1,"time":1271977712,"description":"Alicia Keys - Teenage Love Affair [Official Video] AVI VIDEO &lt;a class=&quot;__cf_email__&quot; href=&quot;/cdn-cgi/l/email-protection&quot; data-cfemail=&quot;c3908b8391eda2b5aa&quot;&gt;[email&amp;#160;protected]&lt;/a&gt;&lt;script cf-hash='f9e31' type=&quot;text/javascript&quot;&gt;\n/* &lt;![CDATA[ */!function(){try{var t=&quot;currentScript&quot;in document?document.currentScript:function(){for(var t=document.getElementsByTagName(&quot;script&quot;),e=t.length;e--;)if(t[e].getAttribute(&quot;cf-hash&quot;))return t[e]}();if(t&amp;&amp;t.previousSibling){var e,r,n,i,c=t.previousSibling,a=c.getAttribute(&quot;data-cfemail&quot;);if(a){for(e=&quot;&quot;,r=parseInt(a.substr(0,2),16),n=2;a.length-n;n+=2)i=parseInt(a.substr(n,2),16)^r,e+=String.fromCharCode(i);e=document.createTextNode(e),c.parentNode.replaceChild(e,c)}}}catch(u){}}();/* ]]&gt; */&lt;/script&gt;","torrent":{"xt":"urn:btih:2399205ea49963a80bd9dc03b09f6dd583232e20","amp;dn":"Alicia+Keys+-+Teenage+Love+Affair+%5BOfficial+Video%5D+AVI+VIDEO+SH%40","amp;tr":["udp%3A%2F%2Ftracker.openbittorrent.com%3A80","udp%3A%2F%2Fopen.demonii.com%3A1337","udp%3A%2F%2Ftracker.coppersurfer.tk%3A6969","udp%3A%2F%2Fexodus.desync.com%3A6969"],"infoHash":"2399205ea49963a80bd9dc03b09f6dd583232e20","infoHashBuffer":{"type":"Buffer","data":[35,153,32,94,164,153,99,168,11,217,220,3,176,159,109,213,131,35,46,32]},"announce":[],"urlList":[]}}