{"title":"VA-DJ_whiteowl_white_owl_drop_that_79-(web)-2009-DjLeak","uid":5048058,"size":76888825,"categoryP":"audio","categoryS":"music","magnet":"?xt=urn:btih:2cb70e001dddba5aa4aa0473bc1e93c74aeb71ea&amp;dn=VA-DJ_whiteowl_white_owl_drop_that_79-%28web%29-2009-DjLeak&amp;tr=udp%3A%2F%2Ftracker.openbittorrent.com%3A80&amp;tr=udp%3A%2F%2Fopen.demonii.com%3A1337&amp;tr=udp%3A%2F%2Ftracker.coppersurfer.tk%3A6969&amp;tr=udp%3A%2F%2Fexodus.desync.com%3A6969","seeders":0,"leechers":0,"uploader":"focused1804","files":30,"time":1249748648,"description":"01 -Jadakiss- styles P &amp; sheek louch-Move     [04:06]\n   02 -Styles P &amp; M.O.P-Bang bang                [04:21]\n   03 -Lil wayne-My band                         [00:56]\n   04 -Jay Z-Blue print 3 freestyle (new verses) [03:23]\n   05 -Eminem-Die already (dissin soulja boy)    [02:17]\n   06 -Mike knox-G unit philly interlude         [00:39]\n   07 -Mike knox-Mr scarface                     [03:36]\n   08 -Mase-Shutdown the city                    [04:23]\n   09 -Hell rell-Jr writer - yeah yeah           [03:36]\n   10 -Hell rell-I got beef                      [02:37]\n   11 -Slaughter house-Cuckoo                    [04:17]\n   12 -Joe budden &amp; royce 5'9-Lyrical murda      [03:29]\n   13 -Stack bundles &amp; the riot squad-What the   [04:20]\n       roc is cookin\n   14 -Young chris- wale &amp; rhymefest-Get down    [02:40]\n   15 -Havoc-Freestyle                           [00:57]\n   16 -Jr writer-The hustler                     [02:01]\n   17 -Whiteowldropthat-Whiteowl                 [00:10]\n   18 -Slaughter house-Killaz                    [04:04]\n   19 -L black-How 2 rob (philly style)          [03:47]\n   20 -M-uno-Freestyle                           [01:32]\n   21 -Big lou-Jackin beats - dissin fat joe     [07:45]\n   22 -Corporal asskick &amp; rockaway jah-Whiteowl  [03:06]\n       anthem\n   23 -G-note-I told ya'll                       [02:49]\n   24 -Hell rell-Top gunna                       [03:17]\n   25 -Jr writer-Freestyle                       [01:14]\n   26 -Slaughter house-Microphone fiends         [04:23]\n\n\n\n                                            Time:[79:45]min\n                                            Size:[ 73,2]MB\n","torrent":{"xt":"urn:btih:2cb70e001dddba5aa4aa0473bc1e93c74aeb71ea","amp;dn":"VA-DJ_whiteowl_white_owl_drop_that_79-%28web%29-2009-DjLeak","amp;tr":["udp%3A%2F%2Ftracker.openbittorrent.com%3A80","udp%3A%2F%2Fopen.demonii.com%3A1337","udp%3A%2F%2Ftracker.coppersurfer.tk%3A6969","udp%3A%2F%2Fexodus.desync.com%3A6969"],"infoHash":"2cb70e001dddba5aa4aa0473bc1e93c74aeb71ea","infoHashBuffer":{"type":"Buffer","data":[44,183,14,0,29,221,186,90,164,170,4,115,188,30,147,199,74,235,113,234]},"announce":[],"urlList":[]}}