{"title":"[X360]Forza_Motorsport_3[PAL][DVD2][www.X360SOS.com]","uid":5124061,"size":7283378035,"categoryP":"games","categoryS":"xbox360","magnet":"?xt=urn:btih:324b590efbe4a0268abdd4589a8a7b3fb9b01a3f&amp;dn=%5BX360%5DForza_Motorsport_3%5BPAL%5D%5BDVD2%5D%5Bwww.X360SOS.com%5D&amp;tr=udp%3A%2F%2Ftracker.openbittorrent.com%3A80&amp;tr=udp%3A%2F%2Fopen.demonii.com%3A1337&amp;tr=udp%3A%2F%2Ftracker.coppersurfer.tk%3A6969&amp;tr=udp%3A%2F%2Fexodus.desync.com%3A6969","seeders":0,"leechers":0,"uploader":"Markuf","files":38,"time":1255518812,"description":"Visit us at X360SOS.com!\n\n----------------------------------------------------------------\n                            GAME iNFO\n----------------------------------------------------------------\n\nGAME NAME                       :            Forza Motor 3 DVD 2\nGAME REGiON                     :                            PAL\nREGION FREE                     :                             NO\nGENRE                           :                     SimulaciÃƒÂ³n\nLANGUAGE/S                      :                           EN/?\nUPLOAD DATE                     :                       13/10/09\n\n----------------------------------------------------------------\n----------&gt; X360SOS.COM DO NOT HOST ANY ILLEGAL FILE  2009  X360SOS.COM ","torrent":{"xt":"urn:btih:324b590efbe4a0268abdd4589a8a7b3fb9b01a3f","amp;dn":"%5BX360%5DForza_Motorsport_3%5BPAL%5D%5BDVD2%5D%5Bwww.X360SOS.com%5D","amp;tr":["udp%3A%2F%2Ftracker.openbittorrent.com%3A80","udp%3A%2F%2Fopen.demonii.com%3A1337","udp%3A%2F%2Ftracker.coppersurfer.tk%3A6969","udp%3A%2F%2Fexodus.desync.com%3A6969"],"infoHash":"324b590efbe4a0268abdd4589a8a7b3fb9b01a3f","infoHashBuffer":{"type":"Buffer","data":[50,75,89,14,251,228,160,38,138,189,212,88,154,138,123,63,185,176,26,63]},"announce":[],"urlList":[]}}