{"title":"Streetblowjobs - Amelia Rose - Streets to the sheets","uid":5567003,"size":562274684,"categoryP":"porn","categoryS":"movie_clips","magnet":"?xt=urn:btih:36a8bea9e5c60e3f047346e76878a616396e4cdc&amp;dn=Streetblowjobs+-+Amelia+Rose+-+Streets+to+the+sheets&amp;tr=udp%3A%2F%2Ftracker.openbittorrent.com%3A80&amp;tr=udp%3A%2F%2Fopen.demonii.com%3A1337&amp;tr=udp%3A%2F%2Ftracker.coppersurfer.tk%3A6969&amp;tr=udp%3A%2F%2Fexodus.desync.com%3A6969","seeders":0,"leechers":1,"uploader":"beta2008x","files":1,"time":1274015337,"description":" &lt;a href=&quot;http://www.dumppix.com/viewer.php?file=q56qa_amelia063.jpg&quot; rel=&quot;nofollow&quot; target=&quot;_NEW&quot;&gt;http://www.dumppix.com/viewer.php?file=q56qa_amelia063.jpg&lt;/a&gt;\n &lt;a href=&quot;\nhttp://www.dumppix.com/viewer.php?file=bpqzo_amelia189.jpg&quot; rel=&quot;nofollow&quot; target=&quot;_NEW&quot;&gt;\nhttp://www.dumppix.com/viewer.php?file=bpqzo_amelia189.jpg&lt;/a&gt;\n &lt;a href=&quot;\nhttp://www.dumppix.com/viewer.php?file=v0rs_Streetblowjobs_Ameli.jpg&quot; rel=&quot;nofollow&quot; target=&quot;_NEW&quot;&gt;\nhttp://www.dumppix.com/viewer.php?file=v0rs_Streetblowjobs_Ameli.jpg&lt;/a&gt;\n\n\n\nCast\nVoodoo Amelia Rose\n\nSun May 16, 2010\nToday I went to watch a soft ball game at the park but for some reason there was no game going on. I decided to sit there for a few minutes to see if some people started to show up but no luck. Then I happened to see this lovely young lady walking by looking for her lost dog. She only had a 20$ reward for the dog if anyone found him. I decided to try to help her out. If she would hang out with me for a little bit I would give her 100$ in which she could use as the reward money if someone found the dog. Well long story short we hung out she gave me a great blowjob and I gave her what I promised. We all left happy. Enjoy!\n\n\n\n\n","torrent":{"xt":"urn:btih:36a8bea9e5c60e3f047346e76878a616396e4cdc","amp;dn":"Streetblowjobs+-+Amelia+Rose+-+Streets+to+the+sheets","amp;tr":["udp%3A%2F%2Ftracker.openbittorrent.com%3A80","udp%3A%2F%2Fopen.demonii.com%3A1337","udp%3A%2F%2Ftracker.coppersurfer.tk%3A6969","udp%3A%2F%2Fexodus.desync.com%3A6969"],"infoHash":"36a8bea9e5c60e3f047346e76878a616396e4cdc","infoHashBuffer":{"type":"Buffer","data":[54,168,190,169,229,198,14,63,4,115,70,231,104,120,166,22,57,110,76,220]},"announce":[],"urlList":[]}}