{"title":"Paul Carrack - It Ain't Over mp3","uid":5119787,"size":44450982,"categoryP":"audio","categoryS":"music","magnet":"?xt=urn:btih:3980f89cd58f478763cb5cf89c6dcd9fc813ddd3&amp;dn=Paul+Carrack+-+It+Ain%5C%27t+Over+mp3&amp;tr=udp%3A%2F%2Ftracker.openbittorrent.com%3A80&amp;tr=udp%3A%2F%2Fopen.demonii.com%3A1337&amp;tr=udp%3A%2F%2Ftracker.coppersurfer.tk%3A6969&amp;tr=udp%3A%2F%2Fexodus.desync.com%3A6969","seeders":0,"leechers":1,"uploader":"dizzycactus","files":14,"time":1255270483,"description":"Paul Carrack - It Ain't Over. 11 tracks mp3.","torrent":{"xt":"urn:btih:3980f89cd58f478763cb5cf89c6dcd9fc813ddd3","amp;dn":"Paul+Carrack+-+It+Ain%5C%27t+Over+mp3","amp;tr":["udp%3A%2F%2Ftracker.openbittorrent.com%3A80","udp%3A%2F%2Fopen.demonii.com%3A1337","udp%3A%2F%2Ftracker.coppersurfer.tk%3A6969","udp%3A%2F%2Fexodus.desync.com%3A6969"],"infoHash":"3980f89cd58f478763cb5cf89c6dcd9fc813ddd3","infoHashBuffer":{"type":"Buffer","data":[57,128,248,156,213,143,71,135,99,203,92,248,156,109,205,159,200,19,221,211]},"announce":[],"urlList":[]}}