{"title":"Brave A Warriors Tale [MULTI5][XBOX360][gamerguuy]","uid":5046394,"size":6535339655,"categoryP":"games","categoryS":"xbox360","magnet":"?xt=urn:btih:482a6be14899bb1f11552f0a99b187b0c741e35a&amp;dn=Brave+A+Warriors+Tale+%5BMULTI5%5D%5BXBOX360%5D%5Bgamerguuy%5D&amp;tr=udp%3A%2F%2Ftracker.openbittorrent.com%3A80&amp;tr=udp%3A%2F%2Fopen.demonii.com%3A1337&amp;tr=udp%3A%2F%2Ftracker.coppersurfer.tk%3A6969&amp;tr=udp%3A%2F%2Fexodus.desync.com%3A6969","seeders":0,"leechers":1,"uploader":"gamerguuy","files":-1,"time":1249659113,"description":"Category: XBOX360\nLanguage: EspaÃƒÂ±ol,English,French,Italian,German\nType:Adventure\nFormat: ISO\nSize: 6.09 GB\nDate: 07-08-2009\n\nThe adventure of the Brave: A Warriors Tale is based on the mythology of Native America. Tells the epic journey of a young Indian who wants to save his tribe wendigo terrible. A journey that will take you for a wonderful interactive world inhabited by extraordinary characters, wild beasts and terrifying evil spirits.","torrent":{"xt":"urn:btih:482a6be14899bb1f11552f0a99b187b0c741e35a","amp;dn":"Brave+A+Warriors+Tale+%5BMULTI5%5D%5BXBOX360%5D%5Bgamerguuy%5D","amp;tr":["udp%3A%2F%2Ftracker.openbittorrent.com%3A80","udp%3A%2F%2Fopen.demonii.com%3A1337","udp%3A%2F%2Ftracker.coppersurfer.tk%3A6969","udp%3A%2F%2Fexodus.desync.com%3A6969"],"infoHash":"482a6be14899bb1f11552f0a99b187b0c741e35a","infoHashBuffer":{"type":"Buffer","data":[72,42,107,225,72,153,187,31,17,85,47,10,153,177,135,176,199,65,227,90]},"announce":[],"urlList":[]}}