{"title":"Nos 18 Ans *2008* [TVRip.XviD-miguel] [Lektor PL]","uid":5662930,"size":735093351,"categoryP":"video","categoryS":"movies","magnet":"?xt=urn:btih:5e851b582ab13e48b6127216d4f9b42beaac1b15&amp;dn=Nos+18+Ans+%2A2008%2A+%5BTVRip.XviD-miguel%5D+%5BLektor+PL%5D&amp;tr=udp%3A%2F%2Ftracker.openbittorrent.com%3A80&amp;tr=udp%3A%2F%2Fopen.demonii.com%3A1337&amp;tr=udp%3A%2F%2Ftracker.coppersurfer.tk%3A6969&amp;tr=udp%3A%2F%2Fexodus.desync.com%3A6969","seeders":0,"leechers":1,"uploader":"miguel1983","files":3,"time":1278035221,"description":"Production....: France\nGenre.........: Comedy\nDate release..: 13.08.2008 [World]\nDirector......: Frederic Berthe\nWriter........: Fausto Brizzi, Eric Assous\nDuration......: 90 min.\nMore..........: http://www.imdb.com/title/tt1092020\n\nPilot :\nIt's their big day: the end of eighteen science for Lucas, his friend Alice, Richard and Maxima Real man who turns out to be the greatest Casanova whole package. On the other side of town, ClÃƒÂ©mence and her friends, sexy romantic Valentine and Clarisse feel the same thrill of expectation. In a few weeks final examinations and end of school forever! At admission and ClÃƒÂ©mence Lucas eyes meet. They feel that this decisive moment in their lives. But rozemocjonowany Lucas ClÃƒÂ©mence forgets to take from her phone number. Do not know him well, none of his friends. Is the boy manages to find it?\n\nCats :\nThÃƒÂ©o Frilet\t ... \tLucas\nValentine Catzeflis\t... \tClemence\nMichel Blanc\t... \tLe professeur Martineau\nArthur Dupont\t... \tMaxime\nJulia Piaton\t... \tSarah\nLisa Manili\t... \tAlice\nPierre Boulanger\t... \tRichard\nBernadette Lafont\t... \tAdele\nVenantino Venantini\t... \tMarcello\nMaruschka Detmers\t... \tLa mere de Clemence\nIris Besse\t... \tValentine\nAnnabel Rohmer\t... \tClarisse\nBartholomew Boutellis\t... \tYvan (as Bartholomew Bouteillis)\nPierre Niney\t... \tLoic\nLucy Ferry\t... \tLaura\n\nData Technical :\n!!! SAMPLE !!!\nAudio.....: Lektor PL\nSubtitles.: None\nVideo.....: XviD 624x336 25.00fps [Stream 00]\nAudio.....: MPEG Audio Layer 3 48000Hz stereo 125kbps [Stream 01]\n\nScreen :\n","torrent":{"xt":"urn:btih:5e851b582ab13e48b6127216d4f9b42beaac1b15","amp;dn":"Nos+18+Ans+%2A2008%2A+%5BTVRip.XviD-miguel%5D+%5BLektor+PL%5D","amp;tr":["udp%3A%2F%2Ftracker.openbittorrent.com%3A80","udp%3A%2F%2Fopen.demonii.com%3A1337","udp%3A%2F%2Ftracker.coppersurfer.tk%3A6969","udp%3A%2F%2Fexodus.desync.com%3A6969"],"infoHash":"5e851b582ab13e48b6127216d4f9b42beaac1b15","infoHashBuffer":{"type":"Buffer","data":[94,133,27,88,42,177,62,72,182,18,114,22,212,249,180,43,234,172,27,21]},"announce":[],"urlList":[]}}