{"title":"Jonah Hex CAM V.O Sub Spanish 2010","uid":5656887,"size":729813476,"categoryP":"video","categoryS":"movies","magnet":"?xt=urn:btih:637a4a9371bde3c6346da4fdfb55c2cf76e0920e&amp;dn=Jonah+Hex+CAM+V.O+Sub+Spanish+2010&amp;tr=udp%3A%2F%2Ftracker.openbittorrent.com%3A80&amp;tr=udp%3A%2F%2Fopen.demonii.com%3A1337&amp;tr=udp%3A%2F%2Ftracker.coppersurfer.tk%3A6969&amp;tr=udp%3A%2F%2Fexodus.desync.com%3A6969","seeders":0,"leechers":0,"uploader":"Mois20","files":1,"time":1277838664,"description":"En el salvaje oeste, Jonah Hex (Josh Brolin) es conocido por tener una cicatriz en la parte derecha de su rostro y vestir un uniforme del ejÃƒÂ©rcito confederado. Fue vendido a los Apalaches por su padre y tuvo que hacerse a sÃƒÂ­ mismo en un mundo tan duro como era el lejano Oeste siendo pistolero y caza recompensas en algunos momentos de su vida. Su ÃƒÂºnico contacto con la gente es a travÃƒÂ©s de la bella Lilah (Megan Fox). AdaptaciÃƒÂ³n del cÃƒÂ³mic del mismo nombre.     ","torrent":{"xt":"urn:btih:637a4a9371bde3c6346da4fdfb55c2cf76e0920e","amp;dn":"Jonah+Hex+CAM+V.O+Sub+Spanish+2010","amp;tr":["udp%3A%2F%2Ftracker.openbittorrent.com%3A80","udp%3A%2F%2Fopen.demonii.com%3A1337","udp%3A%2F%2Ftracker.coppersurfer.tk%3A6969","udp%3A%2F%2Fexodus.desync.com%3A6969"],"infoHash":"637a4a9371bde3c6346da4fdfb55c2cf76e0920e","infoHashBuffer":{"type":"Buffer","data":[99,122,74,147,113,189,227,198,52,109,164,253,251,85,194,207,118,224,146,14]},"announce":[],"urlList":[]}}