{"title":"Friday.Trilogy(1995-2000-2002).NTS-PAL.DVD5-9-PRCL","uid":5058216,"size":19857026036,"categoryP":"video","categoryS":"movies_dvdr","magnet":"?xt=urn:btih:652fbe88053649f1fad4fdce34cfa0ba63563deb&amp;dn=Friday.Trilogy%281995-2000-2002%29.NTS-PAL.DVD5-9-PRCL&amp;tr=udp%3A%2F%2Ftracker.openbittorrent.com%3A80&amp;tr=udp%3A%2F%2Fopen.demonii.com%3A1337&amp;tr=udp%3A%2F%2Ftracker.coppersurfer.tk%3A6969&amp;tr=udp%3A%2F%2Fexodus.desync.com%3A6969","seeders":0,"leechers":0,"uploader":"grebyn11","files":42,"time":1250533908,"description":"Friday.1995.WS.DVDR.NTSC-LHD\n audio:english\n subtitle:french, spanish, english\n\nNext.Friday.2000.HUN.PAL.DVDR-rtz6\n audio:hungarian, rusian, english\n subtitle:czech, poland, hungarian, rusian, english \n\nFriday After Next 2002 DVD9 PAL MULTISUBS\n aurio:english\n subtitle:english, russian, HRVATSKI, czech, magyar, polish, romanian, SRPSKI, slovenski\n\n\nPLEASE SEED THOSE DVD'S ARE VERY RARE!!!","torrent":{"xt":"urn:btih:652fbe88053649f1fad4fdce34cfa0ba63563deb","amp;dn":"Friday.Trilogy%281995-2000-2002%29.NTS-PAL.DVD5-9-PRCL","amp;tr":["udp%3A%2F%2Ftracker.openbittorrent.com%3A80","udp%3A%2F%2Fopen.demonii.com%3A1337","udp%3A%2F%2Ftracker.coppersurfer.tk%3A6969","udp%3A%2F%2Fexodus.desync.com%3A6969"],"infoHash":"652fbe88053649f1fad4fdce34cfa0ba63563deb","infoHashBuffer":{"type":"Buffer","data":[101,47,190,136,5,54,73,241,250,212,253,206,52,207,160,186,99,86,61,235]},"announce":[],"urlList":[]}}