{"title":"Housewife Bangers 13 (2009) By josvila","uid":5097861,"size":1460363264,"categoryP":"porn","categoryS":"movies","magnet":"?xt=urn:btih:679ff86636d036e29983dbcb79fffaaef33ce024&amp;dn=Housewife+Bangers+13+%282009%29+By+josvila&amp;tr=udp%3A%2F%2Ftracker.openbittorrent.com%3A80&amp;tr=udp%3A%2F%2Fopen.demonii.com%3A1337&amp;tr=udp%3A%2F%2Ftracker.coppersurfer.tk%3A6969&amp;tr=udp%3A%2F%2Fexodus.desync.com%3A6969","seeders":0,"leechers":0,"uploader":"josvila","files":-1,"time":1253728098,"description":"Housewife Bangers 13 (2009) \n\nStudio  Pink Visual \nRelease Date  Aug 15, 2009 \nCategory  All Sex \nStarring  Mika Kani, Tabitha Tucker, Tiffany Lynn, Margarita Rose, Cassie Sweets \n\nWhat happens when the husband of a sexy ass wife gets in a bind and can't get himself out of it? His wife ends up bending over to save his sorry ass yet again - that's what! They may be reluctant at first, but in the end these horny housewives ...    Full Descriptionare willing and able to take care of the business at hand while their weak-ass &quot;man&quot; looks on, sometimes in shame, and sometimes like he might just be getting off on his woman getting her pussy pounded by someone else.\n","torrent":{"xt":"urn:btih:679ff86636d036e29983dbcb79fffaaef33ce024","amp;dn":"Housewife+Bangers+13+%282009%29+By+josvila","amp;tr":["udp%3A%2F%2Ftracker.openbittorrent.com%3A80","udp%3A%2F%2Fopen.demonii.com%3A1337","udp%3A%2F%2Ftracker.coppersurfer.tk%3A6969","udp%3A%2F%2Fexodus.desync.com%3A6969"],"infoHash":"679ff86636d036e29983dbcb79fffaaef33ce024","infoHashBuffer":{"type":"Buffer","data":[103,159,248,102,54,208,54,226,153,131,219,203,121,255,250,174,243,60,224,36]},"announce":[],"urlList":[]}}