{"title":"Survivor Philippines Palau 45","uid":5127267,"size":1229691737,"categoryP":"video","categoryS":"tv_shows","magnet":"?xt=urn:btih:736ed152db9bf6ec06b8027b6b847470d8ff7279&amp;dn=Survivor+Philippines+Palau+45&amp;tr=udp%3A%2F%2Ftracker.openbittorrent.com%3A80&amp;tr=udp%3A%2F%2Fopen.demonii.com%3A1337&amp;tr=udp%3A%2F%2Ftracker.coppersurfer.tk%3A6969&amp;tr=udp%3A%2F%2Fexodus.desync.com%3A6969","seeders":0,"leechers":0,"uploader":"quackdoctor","files":1,"time":1255743439,"description":"Survivor Philippines Palau 45\n\nvid size: 640 x 480\nfile format: wmv\nspoken language: English/Tagalog\n\nplease help me seed.","torrent":{"xt":"urn:btih:736ed152db9bf6ec06b8027b6b847470d8ff7279","amp;dn":"Survivor+Philippines+Palau+45","amp;tr":["udp%3A%2F%2Ftracker.openbittorrent.com%3A80","udp%3A%2F%2Fopen.demonii.com%3A1337","udp%3A%2F%2Ftracker.coppersurfer.tk%3A6969","udp%3A%2F%2Fexodus.desync.com%3A6969"],"infoHash":"736ed152db9bf6ec06b8027b6b847470d8ff7279","infoHashBuffer":{"type":"Buffer","data":[115,110,209,82,219,155,246,236,6,184,2,123,107,132,116,112,216,255,114,121]},"announce":[],"urlList":[]}}