{"title":"Antinomus - Black Metal Is Dead","uid":5512504,"size":39481662,"categoryP":"audio","categoryS":"music","magnet":"?xt=urn:btih:897af755b74b8c278fd164c62c16a5b44638941d&amp;dn=Antinomus+-+Black+Metal+Is+Dead&amp;tr=udp%3A%2F%2Ftracker.openbittorrent.com%3A80&amp;tr=udp%3A%2F%2Fopen.demonii.com%3A1337&amp;tr=udp%3A%2F%2Ftracker.coppersurfer.tk%3A6969&amp;tr=udp%3A%2F%2Fexodus.desync.com%3A6969","seeders":0,"leechers":1,"uploader":"Rumore","files":-1,"time":1272116973,"description":"Arist: Antinomus\nAlbum: Black Metal Is Dead\n\nYear: 2009\nGenre: Techno / Electro","torrent":{"xt":"urn:btih:897af755b74b8c278fd164c62c16a5b44638941d","amp;dn":"Antinomus+-+Black+Metal+Is+Dead","amp;tr":["udp%3A%2F%2Ftracker.openbittorrent.com%3A80","udp%3A%2F%2Fopen.demonii.com%3A1337","udp%3A%2F%2Ftracker.coppersurfer.tk%3A6969","udp%3A%2F%2Fexodus.desync.com%3A6969"],"infoHash":"897af755b74b8c278fd164c62c16a5b44638941d","infoHashBuffer":{"type":"Buffer","data":[137,122,247,85,183,75,140,39,143,209,100,198,44,22,165,180,70,56,148,29]},"announce":[],"urlList":[]}}