{"title":"Angels.And.Demons.DVDRip.XviD-iMBT-[tracker.BTARENA.org].avi","uid":5069715,"size":1479181818,"categoryP":"video","categoryS":"movies","magnet":"?xt=urn:btih:b3d2ef0e78cec29b9ba12bf28556131c60e618e3&amp;dn=Angels.And.Demons.DVDRip.XviD-iMBT-%5Btracker.BTARENA.org%5D.avi&amp;tr=udp%3A%2F%2Ftracker.openbittorrent.com%3A80&amp;tr=udp%3A%2F%2Fopen.demonii.com%3A1337&amp;tr=udp%3A%2F%2Ftracker.coppersurfer.tk%3A6969&amp;tr=udp%3A%2F%2Fexodus.desync.com%3A6969","seeders":0,"leechers":0,"uploader":"AiTB","files":4,"time":1251291986,"description":"info, sample, subs\n &lt;a href=&quot;\nhttp://www.btarena.org/movies/dvdrip/Angels-And-Demons-DVDRip-XviD-iMBT&quot; rel=&quot;nofollow&quot; target=&quot;_NEW&quot;&gt;\nhttp://www.btarena.org/movies/dvdrip/Angels-And-Demons-DVDRip-XviD-iMBT&lt;/a&gt;\n\n\n\n//if new tpb owners won't accept our torrents, move to           &lt;a href=&quot;\nhttp://tracker.btarena.org&quot; rel=&quot;nofollow&quot; target=&quot;_NEW&quot;&gt;\nhttp://tracker.btarena.org&lt;/a&gt;","torrent":{"xt":"urn:btih:b3d2ef0e78cec29b9ba12bf28556131c60e618e3","amp;dn":"Angels.And.Demons.DVDRip.XviD-iMBT-%5Btracker.BTARENA.org%5D.avi","amp;tr":["udp%3A%2F%2Ftracker.openbittorrent.com%3A80","udp%3A%2F%2Fopen.demonii.com%3A1337","udp%3A%2F%2Ftracker.coppersurfer.tk%3A6969","udp%3A%2F%2Fexodus.desync.com%3A6969"],"infoHash":"b3d2ef0e78cec29b9ba12bf28556131c60e618e3","infoHashBuffer":{"type":"Buffer","data":[179,210,239,14,120,206,194,155,155,161,43,242,133,86,19,28,96,230,24,227]},"announce":[],"urlList":[]}}