{"title":"MEATSHITS - Almost Complete Discography + Cover Scans_by GS","uid":5132333,"size":609139816,"categoryP":"audio","categoryS":"music","magnet":"?xt=urn:btih:d691c08e938971de6b1b2ae76cdf71ea80627e31&amp;dn=MEATSHITS+-+Almost+Complete+Discography+%2B+Cover+Scans_by+GS&amp;tr=udp%3A%2F%2Ftracker.openbittorrent.com%3A80&amp;tr=udp%3A%2F%2Fopen.demonii.com%3A1337&amp;tr=udp%3A%2F%2Ftracker.coppersurfer.tk%3A6969&amp;tr=udp%3A%2F%2Fexodus.desync.com%3A6969","seeders":0,"leechers":1,"uploader":"Grzechsin","files":-1,"time":1256151801,"description":"***********************************************************************************\n===================================================================================\n+++++++++++++++++++++ MEATSHITS - Almost Complete Discography +++++++++++++++++++++\n===================================================================================\n\nI present U My Collection of MEATSHITS recordings.\n\nGodfathers of Porn Grind / Noise Grind.\n\nIncluding Cover scans of all my CD's and 7&quot;EP's:\n\n&quot;Ecstasy of Death&quot; CD\n&quot;Fuck Frenzy&quot; CD\n&quot;The Second Degree of Torture&quot; CD\n&quot;Gorenography&quot; CD\n&quot;Violence Against Feminist Cunts&quot; CD\n&quot;Sniper on a Fag Parade&quot; CD\n&quot;Give Hate a Chance&quot; split CD w/ CATATONIC EXISTENCE\n\n===================================================================================\n\n + &quot;Whoreible vol.1&quot; CD with some 7&quot; EP's:\n\n&quot;Homosexual Slaughter&quot;\n&quot;Take This and Eat It&quot;\n&quot;Mindfuck Delirium&quot;\n&quot;Another Day of Death&quot; - split w/ NECROPHILIACS\n&quot;Tomb of the Guardian Angel&quot; - split w/ C.S.S.O.\n&quot;Sewer in My Mind&quot; - split w/ DEAD\n&quot;Sexual Abuse&quot;\n&quot;Cry Now, Cry Later&quot; - 3 traxxx from this compilation\nLet Me Kill You, Instead&quot; - BONUS Track from this CD\n\n=================================================================================== &lt;a href=&quot;\nhttp://www.spirit-of-metal.com/groupe-groupe-Meat_Shits-l-en.html&quot; rel=&quot;nofollow&quot; target=&quot;_NEW&quot;&gt;\nhttp://www.spirit-of-metal.com/groupe-groupe-Meat_Shits-l-en.html&lt;/a&gt;\n\n===================================================================================\n\nSTAY BRUTAL, ENJOY &amp; SEED FOR OTHERS!!!\n\n===================================================================================\n***********************************************************************************","torrent":{"xt":"urn:btih:d691c08e938971de6b1b2ae76cdf71ea80627e31","amp;dn":"MEATSHITS+-+Almost+Complete+Discography+%2B+Cover+Scans_by+GS","amp;tr":["udp%3A%2F%2Ftracker.openbittorrent.com%3A80","udp%3A%2F%2Fopen.demonii.com%3A1337","udp%3A%2F%2Ftracker.coppersurfer.tk%3A6969","udp%3A%2F%2Fexodus.desync.com%3A6969"],"infoHash":"d691c08e938971de6b1b2ae76cdf71ea80627e31","infoHashBuffer":{"type":"Buffer","data":[214,145,192,142,147,137,113,222,107,27,42,231,108,223,113,234,128,98,126,49]},"announce":[],"urlList":[]}}