{"title":"VA-Dance_Classics_Pop_Edition_Vol._2-3CD-2010","uid":5559182,"size":268982617,"categoryP":"audio","categoryS":"music","magnet":"?xt=urn:btih:e2f30866c12bfc0cd0d700c7a2c3e9924c875447&amp;dn=VA-Dance_Classics_Pop_Edition_Vol._2-3CD-2010&amp;tr=udp%3A%2F%2Ftracker.openbittorrent.com%3A80&amp;tr=udp%3A%2F%2Fopen.demonii.com%3A1337&amp;tr=udp%3A%2F%2Ftracker.coppersurfer.tk%3A6969&amp;tr=udp%3A%2F%2Fexodus.desync.com%3A6969","seeders":0,"leechers":0,"uploader":"insiderz12","files":33,"time":1273774633,"description":"Artist     : VA\nAlbum      : Dance Classics Pop Edition Vol. 2\nLabel      : Rodeo Media\nGenre      : Dance\nBitrate    : 197 kbps avg\nSource     : CD\nPlaytime   : 03:00:26  (268.MB)\nRls date   : 2010-05-12\nStore date : 2010-00-00\n\n\n[Track List]\n\nDisc 1/3\n--------\n1. Queen - Another One Bites The Dust              3:37\n2. Duran Duran - Wild Boys (Wilder Than Wild Boys  8:01\n   Extended Mix)\n3. David Bowie - Modern Love                       4:48\n4. Steve Winwood - Higher Love (U.K. Extended      7:40\n   Mix)\n5. Eurythmics - Sexcrime (Extended Mix)            7:59\n6. Bryan Ferry - Don't Stop The Dance (12''        5:47\n   Remix)\n7. Culture Club - Do You Really Want To Hurt Me    3:39\n8. Erasure - Sometimes (12'' Mix)                  5:24\n9. Johnny Hates Jazz - I Don't Want To Be A Hero   6:35\n   (Extended Mix)\n10.Living In A Box - Living In A Box (Dance Mix)   6:05\n\nDisc 2/3\n--------\n1. A-HA - Take On Me (Extended Version)            4:50\n2. Simply Red - The Right Thing (Extended          5:37\n   Version)\n3. Sheila E. - Glamourous Life (Club Edit)         6:36\n4. Robert Palmer - I Didn't Mean To Turn You On    6:35\n   (Extended Version)\n5. Billy Idol - Eyes Without A Face                4:53\n6. Crowded House - Don't Dream It's Over           6:14\n   (Extended Version)\n7. Kajagoogoo - Too Shy (12'' Extended Version)    5:27\n8. Kim Wilde - Cambodia                            3:58\n9. Tina Turner - What's Love Got To Do With It     5:49\n   (Extended Version)\n10.Golden Earring - Radar Love (Long Version)      6:23\n\nDisc 3/3\n--------\n1. Whitney Houston - I Wanna Dance With Somebody   8:34\n   (12'' Remix)\n2. Kid Creole &amp; The Coconuts - Annie I'm Not Your  6:25\n   Daddy (Extended Version)\n3. Terence Trent D'arby - Sign Your Name           5:50\n   (Extended Version)\n4. Yazoo - Situation (1982 US Remix)               5:46\n5. ABC - The Look Of Love (US Remix)               7:40\n6. Scritti Politti - Absolute (Extended Version)   6:11\n7. The Human League - Don't You Want Me (ARP       5:57\n   Extended Edit)\n8. Bangles - Walk Like An Egyptian (Extended       5:49\n   Dance Mix)\n9. Feargal Sharkey - A Good Heart                  4:40\n10.Propaganda - Duel (Eye To Eye) (Bitter Sweet)   7:37","torrent":{"xt":"urn:btih:e2f30866c12bfc0cd0d700c7a2c3e9924c875447","amp;dn":"VA-Dance_Classics_Pop_Edition_Vol._2-3CD-2010","amp;tr":["udp%3A%2F%2Ftracker.openbittorrent.com%3A80","udp%3A%2F%2Fopen.demonii.com%3A1337","udp%3A%2F%2Ftracker.coppersurfer.tk%3A6969","udp%3A%2F%2Fexodus.desync.com%3A6969"],"infoHash":"e2f30866c12bfc0cd0d700c7a2c3e9924c875447","infoHashBuffer":{"type":"Buffer","data":[226,243,8,102,193,43,252,12,208,215,0,199,162,195,233,146,76,135,84,71]},"announce":[],"urlList":[]}}