{"title":"Opie and Anthony December 2005","uid":5085465,"size":1042966273,"categoryP":"audio","categoryS":"other","magnet":"?xt=urn:btih:f0656e13b5fe227580095fc1c4a30ed087fd924e&amp;dn=Opie+and+Anthony+December+2005&amp;tr=udp%3A%2F%2Ftracker.openbittorrent.com%3A80&amp;tr=udp%3A%2F%2Fopen.demonii.com%3A1337&amp;tr=udp%3A%2F%2Ftracker.coppersurfer.tk%3A6969&amp;tr=udp%3A%2F%2Fexodus.desync.com%3A6969","seeders":0,"leechers":0,"uploader":"shuazien","files":43,"time":1252683839,"description":"Opie and Anthony December 2005\n\nDon't forget to get your daily Commercial Free O&amp;A episodes from MotherGoose56:  &lt;a href=&quot;\nhttp://thepiratebay.se/user/mothergoose56&quot; rel=&quot;nofollow&quot; target=&quot;_NEW&quot;&gt;\nhttp://thepiratebay.se/user/mothergoose56&lt;/a&gt; \n(In TWO different quality formats!! What a gal! Thank you Mothergoose56!\n\nAlso, if you wana here Ron &amp; Fez (eleven 'til three) check out DrDumbs posts at:  &lt;a href=&quot;\nhttp://thepiratebay.se/user/drdumb/&quot; rel=&quot;nofollow&quot; target=&quot;_NEW&quot;&gt;\nhttp://thepiratebay.se/user/drdumb/&lt;/a&gt;\n\nThanks to the original rippers and encoders. Spread the Virus.\n\nA little heads up, if and/or when The Pirate Bay closes you will still be able\nto get classic OnA at M i n i n o v a, or I s o h u n t, or D e m o n o i d. See you there.\n\nP.S.  When The Pirate Bay goes down try the above sites, I won't be going back to re-post the days that were missed.\n\n\nI'll be taking the weekend off and starting with October '04 when I return on Monday.","torrent":{"xt":"urn:btih:f0656e13b5fe227580095fc1c4a30ed087fd924e","amp;dn":"Opie+and+Anthony+December+2005","amp;tr":["udp%3A%2F%2Ftracker.openbittorrent.com%3A80","udp%3A%2F%2Fopen.demonii.com%3A1337","udp%3A%2F%2Ftracker.coppersurfer.tk%3A6969","udp%3A%2F%2Fexodus.desync.com%3A6969"],"infoHash":"f0656e13b5fe227580095fc1c4a30ed087fd924e","infoHashBuffer":{"type":"Buffer","data":[240,101,110,19,181,254,34,117,128,9,95,193,196,163,14,208,135,253,146,78]},"announce":[],"urlList":[]}}